half_adder.v
module half_adder(Y,C,A,B);
input A,B;
output Y, C;

xor(Y,A,B);
and(C,A,B);

endmodule

full_adder.v
`include "half_adder.v"
module full_adder(A,B,Cin,Cout,Sum);
input A, B;
input Cin;
output Cout, Sum; 

wire x, y,z; 

half_adder hadd1(x,y,A,B);
half_adder hadd2(Sum,z,Cin, x);

or(Cout, y, z);

endmodule

testbench/full_adder_tb.v
`include "full_adder.v"


module full_adder_tb;
	reg a, b, cin;
	wire sum, carry;
	
	full_adder fadd(a,b,cin,carry,sum);

	initial begin
		$dumpfile("./output/full_adder.vcd");
		$dumpvars(0, full_adder_tb);
		// test begin.
        a = 0; b = 0; cin = 0;
        #1;
        a = 0; b = 0; cin = 1;
        #1;
        a = 0; b = 1; cin = 0;
        #1;
        a = 0; b = 1; cin = 1;
        #1;
        a = 1; b = 0; cin = 0;
        #1;
        a = 1; b = 0; cin = 1;
        #1;
        a = 1; b = 1; cin = 0;
        #1;
        a = 1; b = 1; cin = 1;
	end 

endmodule

output/full_adder.vcd
$date
	Tue Oct  8 17:06:23 2024
$end
$version
	Icarus Verilog
$end
$timescale
	1s
$end
$scope module full_adder_tb $end
$var wire 1 ! sum $end
$var wire 1 " carry $end
$var reg 1 # a $end
$var reg 1 $ b $end
$var reg 1 % cin $end
$scope module fadd $end
$var wire 1 # A $end
$var wire 1 $ B $end
$var wire 1 % Cin $end
$var wire 1 " Cout $end
$var wire 1 & z $end
$var wire 1 ' y $end
$var wire 1 ( x $end
$var wire 1 ! Sum $end
$scope module hadd1 $end
$var wire 1 # A $end
$var wire 1 $ B $end
$var wire 1 ' C $end
$var wire 1 ( Y $end
$upscope $end
$scope module hadd2 $end
$var wire 1 % A $end
$var wire 1 ( B $end
$var wire 1 & C $end
$var wire 1 ! Y $end
$upscope $end
$upscope $end
$upscope $end
$enddefinitions $end
$comment Show the parameter values. $end
$dumpall
$end
#0
$dumpvars
0(
0'
0&
0%
0$
0#
0"
0!
$end
#1
1!
1%
#2
1(
0%
1$
#3
1"
0!
1&
1%
#4
0"
1!
0&
0%
0$
1#
#5
1"
0!
1&
1%
#6
0&
0(
1'
0%
1$
#7
1!
1%
